openfeature_provider_hyphen/__init__.py
openfeature_provider_hyphen/cache_client.py
openfeature_provider_hyphen/hooks.py
openfeature_provider_hyphen/hyphen_client.py
openfeature_provider_hyphen/provider.py
openfeature_provider_hyphen/types.py
openfeature_provider_hyphen/utils.py
test_python_asdasda-17.0.0.dist-info/LICENSE
test_python_asdasda-17.0.0.dist-info/METADATA
test_python_asdasda-17.0.0.dist-info/WHEEL
test_python_asdasda-17.0.0.dist-info/RECORD
