Metadata-Version: 2.1
Name: test-python-asdasda
Version: 17.0.0
Summary: testttttttttttttttttttttttt
Home-page: https://github.com/Abraxas-365/test-lf
License: MIT
Author: Abraxas-365
Requires-Python: >=3.8,<4.0
Classifier: License :: OSI Approved :: MIT License
Classifier: Programming Language :: Python :: 3
Classifier: Programming Language :: Python :: 3.8
Classifier: Programming Language :: Python :: 3.9
Classifier: Programming Language :: Python :: 3.10
Classifier: Programming Language :: Python :: 3.11
Classifier: Programming Language :: Python :: 3.12
Requires-Dist: cachetools (>=5.3.2,<6.0.0)
Requires-Dist: openfeature-sdk (==0.7.4)
Requires-Dist: requests (>=2.31.0,<3.0.0)
Project-URL: Repository, https://github.com/Abraxas-365/test-lf
